nepseutils/__init__.py
nepseutils/__main__.py
nepseutils/constants.py
nepseutils/version.py
nepseutils/core/account.py
nepseutils/core/errors.py
nepseutils/core/issue.py
nepseutils/core/meroshare.py
nepseutils/core/portfolio.py
nepseutils/utils/__init__.py
nepseutils/utils/config_converter.py
nepseutils/utils/decorators.py
nepseutils/utils/logging.py
nepseutils-0.4.9.dist-info/METADATA
nepseutils-0.4.9.dist-info/WHEEL
nepseutils-0.4.9.dist-info/entry_points.txt
nepseutils-0.4.9.dist-info/licenses/LICENSE
nepseutils-0.4.9.dist-info/RECORD
