Metadata-Version: 2.4
Name: nepseutils
Version: 0.4.9
Summary: Collection of scripts to interact with NEPSE related websites!
Project-URL: Repository, https://github.com/arpandaze/nepseutils
Author-email: Arpan Koirala <arpandaze@gmail.com>
License-File: LICENSE
Keywords: meroshare,nepse,tms
Requires-Python: >=3.9
Requires-Dist: cryptography>=41.0.1
Requires-Dist: requests>=2.31.0
Requires-Dist: tabulate>=0.9.0
Requires-Dist: tenacity>=8.2.2
